trydb/__init__.py
trydb/complier/__init__.py
trydb/complier/create_table.py
trydb/complier/insert.py
trydb/complier/select.py
trydb/models/__init__.py
trydb/models/query.py
trydb-0.1.0.dist-info/licenses/LICENSE
trydb-0.1.0.dist-info/METADATA
trydb-0.1.0.dist-info/WHEEL
trydb-0.1.0.dist-info/top_level.txt
trydb-0.1.0.dist-info/RECORD
