Metadata-Version: 2.4
Name: trydb
Version: 0.1.0
Summary: 關於trydb 數據庫Py-package
Home-page: https://github.com/wangtry3417/freecloud.git
Author: WTech
Author-email: wangtry3417@gmail.com
Classifier: Programming Language :: Python :: 3
Classifier: License :: OSI Approved :: MIT License
Classifier: Operating System :: OS Independent
Requires-Python: >=3.6
License-File: LICENSE
Requires-Dist: sqlalchemy
Dynamic: author
Dynamic: author-email
Dynamic: classifier
Dynamic: description
Dynamic: description-content-type
Dynamic: home-page
Dynamic: license-file
Dynamic: requires-dist
Dynamic: requires-python
Dynamic: summary
